hlsfield/__init__.py
hlsfield/apps.py
hlsfield/defaults.py
hlsfield/exceptions.py
hlsfield/fields.py
hlsfield/helpers.py
hlsfield/signals.py
hlsfield/streaming.py
hlsfield/tasks.py
hlsfield/urls.py
hlsfield/utils.py
hlsfield/utils.py.bac
hlsfield/views.py
hlsfield/widgets.py
hlsfield/templates/hlsfield/players/dash_player.html
hlsfield/templates/hlsfield/players/hls_player.html
hlsfield/templates/hlsfield/players/universal_player.html
django_hlsfield-1.0.7.dist-info/METADATA
django_hlsfield-1.0.7.dist-info/WHEEL
django_hlsfield-1.0.7.dist-info/entry_points.txt
django_hlsfield-1.0.7.dist-info/licenses/LICENSE
django_hlsfield-1.0.7.dist-info/RECORD
