Metadata-Version: 2.4
Name: django-hlsfield
Version: 1.0.7
Summary: Django VideoField + HLSVideoField: metadata, preview frame, automatic HLS/DASH, Celery optional.
Project-URL: Homepage, https://github.com/akula993/django-hlsfield
Project-URL: Documentation, https://django-hlsfield.readthedocs.io/
Project-URL: Repository, https://github.com/akula993/django-hlsfield.git
Project-URL: Issues, https://github.com/akula993/django-hlsfield/issues
Project-URL: Changelog, https://github.com/akula993/django-hlsfield/blob/main/CHANGELOG.md
Project-URL: Funding, https://github.com/sponsors/akula993
Project-URL: Bug Reports, https://github.com/akula993/django-hlsfield/issues
Project-URL: Source Code, https://github.com/akula993/django-hlsfield
Author-email: akula993 <akula993@gmail.com>
License: MIT
License-File: LICENSE
Keywords: adaptive,dash,django,ffmpeg,hls,streaming,video
Classifier: Development Status :: 5 - Production/Stable
Classifier: Environment :: Web Environment
Classifier: Framework :: Django
Classifier: Framework :: Django :: 4.2
Classifier: Framework :: Django :: 5.0
Classifier: Framework :: Django :: 5.1
Classifier: Intended Audience :: Developers
Classifier: License :: OSI Approved :: MIT License
Classifier: Natural Language :: English
Classifier: Natural Language :: Russian
Classifier: Operating System :: OS Independent
Classifier: Programming Language :: Python :: 3 :: Only
Classifier: Programming Language :: Python :: 3.10
Classifier: Programming Language :: Python :: 3.11
Classifier: Programming Language :: Python :: 3.12
Classifier: Programming Language :: Python :: 3.13
Classifier: Topic :: Internet :: WWW/HTTP
Classifier: Topic :: Internet :: WWW/HTTP :: Dynamic Content
Classifier: Topic :: Multimedia :: Video
Classifier: Topic :: Multimedia :: Video :: Conversion
Classifier: Topic :: Software Development :: Libraries :: Python Modules
Classifier: Topic :: System :: Archiving
Requires-Python: >=3.10
Requires-Dist: django<6.0,>=4.2
Provides-Extra: ai
Requires-Dist: opencv-python>=4.8.0; extra == 'ai'
Requires-Dist: torch>=2.0.0; extra == 'ai'
Requires-Dist: transformers>=4.30.0; extra == 'ai'
Provides-Extra: all
Requires-Dist: boto3<2.0,>=1.34; extra == 'all'
Requires-Dist: celery<6.0,>=5.3; extra == 'all'
Requires-Dist: pillow>=10.0.0; extra == 'all'
Requires-Dist: prometheus-client>=0.17.0; extra == 'all'
Requires-Dist: python-magic>=0.4.27; extra == 'all'
Requires-Dist: redis>=4.5.0; extra == 'all'
Provides-Extra: azure
Requires-Dist: azure-storage-blob>=12.17.0; extra == 'azure'
Provides-Extra: celery
Requires-Dist: celery<6.0,>=5.3; extra == 'celery'
Provides-Extra: dev
Requires-Dist: black>=23.0.0; extra == 'dev'
Requires-Dist: flake8>=6.0.0; extra == 'dev'
Requires-Dist: isort>=5.12.0; extra == 'dev'
Requires-Dist: mypy>=1.5.0; extra == 'dev'
Requires-Dist: pre-commit>=3.3.0; extra == 'dev'
Requires-Dist: pytest-cov>=4.1.0; extra == 'dev'
Requires-Dist: pytest-django>=4.5.2; extra == 'dev'
Requires-Dist: pytest>=7.4.0; extra == 'dev'
Requires-Dist: tox>=4.6.0; extra == 'dev'
Provides-Extra: gcs
Requires-Dist: google-cloud-storage>=2.10.0; extra == 'gcs'
Provides-Extra: magic
Requires-Dist: python-magic>=0.4.27; extra == 'magic'
Provides-Extra: monitoring
Requires-Dist: prometheus-client>=0.17.0; extra == 'monitoring'
Provides-Extra: preview
Requires-Dist: pillow>=10.0.0; extra == 'preview'
Provides-Extra: redis
Requires-Dist: redis>=4.5.0; extra == 'redis'
Provides-Extra: s3
Requires-Dist: boto3<2.0,>=1.34; extra == 's3'
Provides-Extra: sentry
Requires-Dist: sentry-sdk>=1.32.0; extra == 'sentry'
